README.md
setup.py
qtpad/__init__.py
qtpad/child.py
qtpad/common.py
qtpad/gui_child.py
qtpad/gui_preferences.py
qtpad/gui_search.py
qtpad/mother.py
qtpad/preferences.py
qtpad.egg-info/PKG-INFO
qtpad.egg-info/SOURCES.txt
qtpad.egg-info/dependency_links.txt
qtpad.egg-info/entry_points.txt
qtpad.egg-info/requires.txt
qtpad.egg-info/top_level.txt
qtpad/icons/(separator).svg
qtpad/icons/copy.svg
qtpad/icons/copy_line.svg
qtpad/icons/copy_to_clipboard.svg
qtpad/icons/cut.svg
qtpad/icons/cut_line.svg
qtpad/icons/delete.svg
qtpad/icons/fetch_clipboard.svg
qtpad/icons/file_active.svg
qtpad/icons/file_image.svg
qtpad/icons/file_inactive.svg
qtpad/icons/file_pinned.svg
qtpad/icons/folder_active.svg
qtpad/icons/folder_inactive.svg
qtpad/icons/folders_list.svg
qtpad/icons/hide.svg
qtpad/icons/hide_all.svg
qtpad/icons/load_all_folders.svg
qtpad/icons/move_to_folder.svg
qtpad/icons/new_note.svg
qtpad/icons/notes_list.svg
qtpad/icons/paste.svg
qtpad/icons/pin.svg
qtpad/icons/pin_title.svg
qtpad/icons/preferences.svg
qtpad/icons/qtpad.svg
qtpad/icons/quit.svg
qtpad/icons/redo.svg
qtpad/icons/rename.svg
qtpad/icons/reset_positions.svg
qtpad/icons/reverse_all.svg
qtpad/icons/save_as.svg
qtpad/icons/search.svg
qtpad/icons/selection_to_lowercase.svg
qtpad/icons/selection_to_uppercase.svg
qtpad/icons/show_all.svg
qtpad/icons/sort_selection.svg
qtpad/icons/special_paste.svg
qtpad/icons/style.svg
qtpad/icons/toggle_actives.svg
qtpad/icons/toggle_sizegrip.svg
qtpad/icons/toggle_wordwrap.svg
qtpad/icons/tray.svg
qtpad/icons/undo.svg
qtpad/icons/unload_all_folders.svg